biotime/__init__.py
biotime/core.py
biotime/exceptions.py
biotime/utils.py
biotime-1.1.dist-info/licenses/LICENSE
biotime-1.1.dist-info/METADATA
biotime-1.1.dist-info/WHEEL
biotime-1.1.dist-info/top_level.txt
biotime-1.1.dist-info/RECORD
