Metadata-Version: 2.4
Name: biotime
Version: 1.1
Summary: Python client for working with ZKBioTime API
Author-email: rozievich <oybekrozievich@gmail.com>
License: MIT License
Project-URL: Homepage, https://github.com/rozievich/biotime
Project-URL: Repository, https://github.com/rozievich/biotime
Project-URL: Issues, https://github.com/rozievich/biotime/issues
Requires-Python: >=3.8
License-File: LICENSE
Requires-Dist: requests>=2.28.0
Provides-Extra: dev
Requires-Dist: pytest; extra == "dev"
Requires-Dist: black; extra == "dev"
Requires-Dist: flake8; extra == "dev"
Dynamic: license-file
